Workbook

Sheet Item_Master
C1: Items: Jugaad Hardware & Tools
A3: Item ID | B3: Item Name | C3: Category | D3: Brand | E3: Unit | F3: Cost Price | G3: Selling Price
A4: HW-0001 | B4: Dulux Enamel Paint 4L | C4: Paints & Coatings | D4: Dulux | E4: each | F4: 1540 | G4: 2160
A5: HW-0002 | B5: Philips PVC Wire 2.5 sqmm | C5: Electrical | D5: Philips | E5: each | F5: 1720 | G5: 2120
A6: HW-0003 | B6: Karam Ear Plugs Silicone | C6: Safety Gear | D6: Karam | E6: each | F6: 650 | G6: 930
A7: HW-0004 | B7: Stanley Claw Hammer 8oz | C7: Hand Tools | D7: Stanley | E7: unit | F7: 1020 | G7: 1330
A8: HW-0005 | B8: Europa Door Stopper Floor | C8: Hardware | D8: Europa | E8: each | F8: 1060 | G8: 1320
A9: HW-0006 | B9: Stanley Adjustable Wrench 12 inch | C9: Hand Tools | D9: Stanley | E9: each | F9: 1520 | G9: 1810
A10: HW-0007 | B10: Mallcom Safety Harness Full Body | C10: Safety Gear | D10: Mallcom | E10: each | F10: 2860 | G10: 4060
A11: HW-0008 | B11: Europa Bracket L-Shape | C11: Hardware | D11: Europa | E11: each | F11: 1470 | G11: 1920
A12: HW-0009 | B12: Loctite Masking Tape 24mm | C12: Adhesives & Sealants | D12: Loctite | E12: each | F12: 450 | G12: 540
A13: HW-0010 | B13: 3M Safety Goggles Clear | C13: Safety Gear | D13: 3M | E13: each | F13: 800 | G13: 1020
A14: HW-0011 | B14: Bosi Screwdriver Set 12 pc | C14: Hand Tools | D14: Bosi | E14: each | F14: 1320 | G14: 1630
A15: HW-0012 | B15: TVS Allen Key Set Imperial | C15: Hand Tools | D15: TVS | E15: pack | F15: 240 | G15: 300
... A353: HW-0350 | B353: Stanley Bench Grinder 6 inch | C353: Power Tools | D353: Stanley | E353: each | F353: 9380 | G353: 12720

Sheet Sales
C1: Sales: Jugaad Hardware & Tools
A3: Sale ID | B3: Date | C3: Item ID | D3: Quantity | E3: Invoice No | F3: Sale Value | G3: Month
A4: SALE-00001 | B4: 45931 | C4: HW-0009 | D4: 28 | E4: INV-23034 | F4: =D4*_xlfn.XLOOKUP(C4,Item_Master!A:A,Item_Master!G:G) -> 15120 | G4: =TEXT(B4,"MMM YYYY") -> Oct 2025
A5: SALE-00002 | B5: 45931 | C5: HW-0010 | D5: 8 | E5: INV-59824 | F5: =D5*_xlfn.XLOOKUP(C5,Item_Master!A:A,Item_Master!G:G) -> 8160 | G5: =TEXT(B5,"MMM YYYY") -> Oct 2025
A6: SALE-00003 | B6: 45931 | C6: HW-0014 | D6: 2 | E6: INV-39394 | F6: =D6*_xlfn.XLOOKUP(C6,Item_Master!A:A,Item_Master!G:G) -> 5840 | G6: =TEXT(B6,"MMM YYYY") -> Oct 2025
A7: SALE-00004 | B7: 45931 | C7: HW-0017 | D7: 1 | E7: INV-55587 | F7: =D7*_xlfn.XLOOKUP(C7,Item_Master!A:A,Item_Master!G:G) -> 1540 | G7: =TEXT(B7,"MMM YYYY") -> Oct 2025
A8: SALE-00005 | B8: 45931 | C8: HW-0075 | D8: 27 | E8: INV-80276 | F8: =D8*_xlfn.XLOOKUP(C8,Item_Master!A:A,Item_Master!G:G) -> 38070 | G8: =TEXT(B8,"MMM YYYY") -> Oct 2025
A9: SALE-00006 | B9: 45931 | C9: HW-0083 | D9: 8 | E9: INV-18898 | F9: =D9*_xlfn.XLOOKUP(C9,Item_Master!A:A,Item_Master!G:G) -> 2080 | G9: =TEXT(B9,"MMM YYYY") -> Oct 2025
A10: SALE-00007 | B10: 45931 | C10: HW-0262 | D10: 13 | E10: INV-29283 | F10: =D10*_xlfn.XLOOKUP(C10,Item_Master!A:A,Item_Master!G:G) -> 74750 | G10: =TEXT(B10,"MMM YYYY") -> Oct 2025
A11: SALE-00008 | B11: 45931 | C11: HW-0320 | D11: 15 | E11: INV-45969 | F11: =D11*_xlfn.XLOOKUP(C11,Item_Master!A:A,Item_Master!G:G) -> 26100 | G11: =TEXT(B11,"MMM YYYY") -> Oct 2025
A12: SALE-00009 | B12: 45932 | C12: HW-0039 | D12: 2 | E12: INV-70215 | F12: =D12*_xlfn.XLOOKUP(C12,Item_Master!A:A,Item_Master!G:G) -> 29420 | G12: =TEXT(B12,"MMM YYYY") -> Oct 2025
A13: SALE-00010 | B13: 45932 | C13: HW-0051 | D13: 2 | E13: INV-38004 | F13: =D13*_xlfn.XLOOKUP(C13,Item_Master!A:A,Item_Master!G:G) -> 360 | G13: =TEXT(B13,"MMM YYYY") -> Oct 2025
A14: SALE-00011 | B14: 45932 | C14: HW-0052 | D14: 38 | E14: INV-92220 | F14: =D14*_xlfn.XLOOKUP(C14,Item_Master!A:A,Item_Master!G:G) -> 114000 | G14: =TEXT(B14,"MMM YYYY") -> Oct 2025
A15: SALE-00012 | B15: 45932 | C15: HW-0123 | D15: 8 | E15: INV-76998 | F15: =D15*_xlfn.XLOOKUP(C15,Item_Master!A:A,Item_Master!G:G) -> 8160 | G15: =TEXT(B15,"MMM YYYY") -> Oct 2025
... A1890: SALE-01887 | B1890: 46112 | C1890: HW-0346 | D1890: 165 | E1890: INV-18439 | F1890: =D1890*_xlfn.XLOOKUP(C1890,Item_Master!A:A,Item_Master!G:G) -> 3172950 | G1890: =TEXT(B1890,"MMM YYYY") -> Mar 2026

Sheet Sales_Analysis
C1: Sales Analysis: Jugaad Hardware & Tools
A3: Item ID | B3: Item Name | C3: Category | D3: Units Sold | E3: Selling Price | F3: Revenue
A4: HW-0001 | B4: =_xlfn.XLOOKUP(A4,Item_Master!A:A,Item_Master!B:B) -> Dulux Enamel Paint 4L | C4: =_xlfn.XLOOKUP(A4,Item_Master!A:A,Item_Master!C:C) -> Paints & Coatings | D4: =SUMIFS(Sales!D:D,Sales!C:C,A4) -> 116 | E4: =_xlfn.XLOOKUP(A4,Item_Master!A:A,Item_Master!G:G) -> 2160 | F4: =D4*E4 -> 250560
A5: HW-0002 | B5: =_xlfn.XLOOKUP(A5,Item_Master!A:A,Item_Master!B:B) -> Philips PVC Wire 2.5 sqmm | C5: =_xlfn.XLOOKUP(A5,Item_Master!A:A,Item_Master!C:C) -> Electrical | D5: =SUMIFS(Sales!D:D,Sales!C:C,A5) -> 96 | E5: =_xlfn.XLOOKUP(A5,Item_Master!A:A,Item_Master!G:G) -> 2120 | F5: =D5*E5 -> 203520
A6: HW-0003 | B6: =_xlfn.XLOOKUP(A6,Item_Master!A:A,Item_Master!B:B) -> Karam Ear Plugs Silicone | C6: =_xlfn.XLOOKUP(A6,Item_Master!A:A,Item_Master!C:C) -> Safety Gear | D6: =SUMIFS(Sales!D:D,Sales!C:C,A6) -> 25 | E6: =_xlfn.XLOOKUP(A6,Item_Master!A:A,Item_Master!G:G) -> 930 | F6: =D6*E6 -> 23250
A7: HW-0004 | B7: =_xlfn.XLOOKUP(A7,Item_Master!A:A,Item_Master!B:B) -> Stanley Claw Hammer 8oz | C7: =_xlfn.XLOOKUP(A7,Item_Master!A:A,Item_Master!C:C) -> Hand Tools | D7: =SUMIFS(Sales!D:D,Sales!C:C,A7) -> 50 | E7: =_xlfn.XLOOKUP(A7,Item_Master!A:A,Item_Master!G:G) -> 1330 | F7: =D7*E7 -> 66500
A8: HW-0005 | B8: =_xlfn.XLOOKUP(A8,Item_Master!A:A,Item_Master!B:B) -> Europa Door Stopper Floor | C8: =_xlfn.XLOOKUP(A8,Item_Master!A:A,Item_Master!C:C) -> Hardware | D8: =SUMIFS(Sales!D:D,Sales!C:C,A8) -> 73 | E8: =_xlfn.XLOOKUP(A8,Item_Master!A:A,Item_Master!G:G) -> 1320 | F8: =D8*E8 -> 96360
A9: HW-0006 | B9: =_xlfn.XLOOKUP(A9,Item_Master!A:A,Item_Master!B:B) -> Stanley Adjustable Wrench 12 inch | C9: =_xlfn.XLOOKUP(A9,Item_Master!A:A,Item_Master!C:C) -> Hand Tools | D9: =SUMIFS(Sales!D:D,Sales!C:C,A9) -> 50 | E9: =_xlfn.XLOOKUP(A9,Item_Master!A:A,Item_Master!G:G) -> 1810 | F9: =D9*E9 -> 90500
A10: HW-0007 | B10: =_xlfn.XLOOKUP(A10,Item_Master!A:A,Item_Master!B:B) -> Mallcom Safety Harness Full Body | C10: =_xlfn.XLOOKUP(A10,Item_Master!A:A,Item_Master!C:C) -> Safety Gear | D10: =SUMIFS(Sales!D:D,Sales!C:C,A10) -> 139 | E10: =_xlfn.XLOOKUP(A10,Item_Master!A:A,Item_Master!G:G) -> 4060 | F10: =D10*E10 -> 564340
A11: HW-0008 | B11: =_xlfn.XLOOKUP(A11,Item_Master!A:A,Item_Master!B:B) -> Europa Bracket L-Shape | C11: =_xlfn.XLOOKUP(A11,Item_Master!A:A,Item_Master!C:C) -> Hardware | D11: =SUMIFS(Sales!D:D,Sales!C:C,A11) -> 36 | E11: =_xlfn.XLOOKUP(A11,Item_Master!A:A,Item_Master!G:G) -> 1920 | F11: =D11*E11 -> 69120
A12: HW-0009 | B12: =_xlfn.XLOOKUP(A12,Item_Master!A:A,Item_Master!B:B) -> Loctite Masking Tape 24mm | C12: =_xlfn.XLOOKUP(A12,Item_Master!A:A,Item_Master!C:C) -> Adhesives & Sealants | D12: =SUMIFS(Sales!D:D,Sales!C:C,A12) -> 61 | E12: =_xlfn.XLOOKUP(A12,Item_Master!A:A,Item_Master!G:G) -> 540 | F12: =D12*E12 -> 32940
A13: HW-0010 | B13: =_xlfn.XLOOKUP(A13,Item_Master!A:A,Item_Master!B:B) -> 3M Safety Goggles Clear | C13: =_xlfn.XLOOKUP(A13,Item_Master!A:A,Item_Master!C:C) -> Safety Gear | D13: =SUMIFS(Sales!D:D,Sales!C:C,A13) -> 177 | E13: =_xlfn.XLOOKUP(A13,Item_Master!A:A,Item_Master!G:G) -> 1020 | F13: =D13*E13 -> 180540
A14: HW-0011 | B14: =_xlfn.XLOOKUP(A14,Item_Master!A:A,Item_Master!B:B) -> Bosi Screwdriver Set 12 pc | C14: =_xlfn.XLOOKUP(A14,Item_Master!A:A,Item_Master!C:C) -> Hand Tools | D14: =SUMIFS(Sales!D:D,Sales!C:C,A14) -> 46 | E14: =_xlfn.XLOOKUP(A14,Item_Master!A:A,Item_Master!G:G) -> 1630 | F14: =D14*E14 -> 74980
A15: HW-0012 | B15: =_xlfn.XLOOKUP(A15,Item_Master!A:A,Item_Master!B:B) -> TVS Allen Key Set Imperial | C15: =_xlfn.XLOOKUP(A15,Item_Master!A:A,Item_Master!C:C) -> Hand Tools | D15: =SUMIFS(Sales!D:D,Sales!C:C,A15) -> 164 | E15: =_xlfn.XLOOKUP(A15,Item_Master!A:A,Item_Master!G:G) -> 300 | F15: =D15*E15 -> 49200
... A353: HW-0350 | B353: =_xlfn.XLOOKUP(A353,Item_Master!A:A,Item_Master!B:B) -> Stanley Bench Grinder 6 inch | C353: =_xlfn.XLOOKUP(A353,Item_Master!A:A,Item_Master!C:C) -> Power Tools | D353: =SUMIFS(Sales!D:D,Sales!C:C,A353) -> 14 | E353: =_xlfn.XLOOKUP(A353,Item_Master!A:A,Item_Master!G:G) -> 12720 | F353: =D353*E353 -> 178080

Sheet Charts
A1: Charts: Jugaad Hardware & Tools
A4: Revenue by Category | D4: Monthly Revenue | H4: Top 10 Items by Revenue
A5: Category | B5: Revenue | D5: Month | E5: Revenue | H5: Item | I5: Revenue
A6: Power Tools | B6: =SUMIFS(Sales_Analysis!F:F,Sales_Analysis!C:C,A6) -> 92946470 | D6: Oct 2025 | E6: =SUMIFS(Sales!F:F,Sales!G:G,D6) -> 18035400 | H6: =_xlfn.XLOOKUP(I6,Sales_Analysis!F:F,Sales_Analysis!B:B) -> Crompton Cordless Drill 20V Pro | I6: =LARGE(Sales_Analysis!F:F,10) -> 2930620
A7: Hand Tools | B7: =SUMIFS(Sales_Analysis!F:F,Sales_Analysis!C:C,A7) -> 10622410 | D7: Nov 2025 | E7: =SUMIFS(Sales!F:F,Sales!G:G,D7) -> 19100730 | H7: =_xlfn.XLOOKUP(I7,Sales_Analysis!F:F,Sales_Analysis!B:B) -> Black & Decker Reciprocating Saw Pro | I7: =LARGE(Sales_Analysis!F:F,9) -> 2999250
A8: Electrical | B8: =SUMIFS(Sales_Analysis!F:F,Sales_Analysis!C:C,A8) -> 10526360 | D8: Dec 2025 | E8: =SUMIFS(Sales!F:F,Sales!G:G,D8) -> 20801620 | H8: =_xlfn.XLOOKUP(I8,Sales_Analysis!F:F,Sales_Analysis!B:B) -> Crompton Rotary Hammer SDS Plus | I8: =LARGE(Sales_Analysis!F:F,8) -> 3177680
A9: Paints & Coatings | B9: =SUMIFS(Sales_Analysis!F:F,Sales_Analysis!C:C,A9) -> 7948370 | D9: Jan 2026 | E9: =SUMIFS(Sales!F:F,Sales!G:G,D9) -> 21612790 | H9: =_xlfn.XLOOKUP(I9,Sales_Analysis!F:F,Sales_Analysis!B:B) -> Stanley Hammer Drill Standard | I9: =LARGE(Sales_Analysis!F:F,7) -> 3412720
A10: Garden Tools | B10: =SUMIFS(Sales_Analysis!F:F,Sales_Analysis!C:C,A10) -> 6288420 | D10: Feb 2026 | E10: =SUMIFS(Sales!F:F,Sales!G:G,D10) -> 16850780 | H10: =_xlfn.XLOOKUP(I10,Sales_Analysis!F:F,Sales_Analysis!B:B) -> Black & Decker Cordless Drill 18V | I10: =LARGE(Sales_Analysis!F:F,6) -> 3433620
A11: Hardware | B11: =SUMIFS(Sales_Analysis!F:F,Sales_Analysis!C:C,A11) -> 6161910 | D11: Mar 2026 | E11: =SUMIFS(Sales!F:F,Sales!G:G,D11) -> 51815790 | H11: =_xlfn.XLOOKUP(I11,Sales_Analysis!F:F,Sales_Analysis!B:B) -> Black & Decker Reciprocating Saw Pro | I11: =LARGE(Sales_Analysis!F:F,5) -> 3520860
A12: Plumbing | B12: =SUMIFS(Sales_Analysis!F:F,Sales_Analysis!C:C,A12) -> 4763090 | H12: =_xlfn.XLOOKUP(I12,Sales_Analysis!F:F,Sales_Analysis!B:B) -> Bosch Heat Gun 2000W | I12: =LARGE(Sales_Analysis!F:F,4) -> 3596010
A13: Safety Gear | B13: =SUMIFS(Sales_Analysis!F:F,Sales_Analysis!C:C,A13) -> 4465000 | H13: =_xlfn.XLOOKUP(I13,Sales_Analysis!F:F,Sales_Analysis!B:B) -> DeWalt Random Orbit Sander 125mm | I13: =LARGE(Sales_Analysis!F:F,3) -> 5055680
A14: Adhesives & Sealants | B14: =SUMIFS(Sales_Analysis!F:F,Sales_Analysis!C:C,A14) -> 3272350 | H14: =_xlfn.XLOOKUP(I14,Sales_Analysis!F:F,Sales_Analysis!B:B) -> DeWalt Random Orbit Sander 150mm | I14: =LARGE(Sales_Analysis!F:F,2) -> 5779120
A15: Fasteners | B15: =SUMIFS(Sales_Analysis!F:F,Sales_Analysis!C:C,A15) -> 1222730 | H15: =_xlfn.XLOOKUP(I15,Sales_Analysis!F:F,Sales_Analysis!B:B) -> DeWalt Bench Grinder 8 inch | I15: =LARGE(Sales_Analysis!F:F,1) -> 6835710

Sheet Sheet5
A1: Fruit | B1: Count
A2: Apple | B2: 10
A3: Banana | B3: 6
A4: Papaya | B4: 18
A5: Grapes | B5: 3
A9: Highest | B9: =LARGE(B2:B5, 1) -> 18
A10: 2nd Highest | B10: =LARGE(B2:B5, 2) -> 10
